art/__init__.py
art/__main__.py
art/art.py
art/art_dic.py
art/art_param.py
art/decor_dic.py
art/test.py
art/test2.py
art/text_dic1.py
art/text_dic2.py
art/text_dic3.py
art-6.2.dist-info/AUTHORS.md
art-6.2.dist-info/LICENSE
art-6.2.dist-info/METADATA
art-6.2.dist-info/WHEEL
art-6.2.dist-info/entry_points.txt
art-6.2.dist-info/top_level.txt
art-6.2.dist-info/RECORD
