Metadata-Version: 2.1
Name: art
Version: 6.2
Summary: ASCII Art Library For Python
Home-page: https://github.com/sepandhaghighi/art
Author: Sepand Haghighi
Author-email: info@ascii-art.site
License: MIT
Project-URL: Webpage, https://www.ascii-art.site
Project-URL: Source, https://github.com/sepandhaghighi/art
Project-URL: Tracker, https://github.com/sepandhaghighi/art/issues
Project-URL: Discord, https://discord.com/invite/FAAyq3QJqP
Keywords: ascii art python3 python text font non-ascii printing
Classifier: Development Status :: 5 - Production/Stable
Classifier: Intended Audience :: Developers
Classifier: Intended Audience :: Education
Classifier: Intended Audience :: End Users/Desktop
Classifier: Intended Audience :: Science/Research
Classifier: Natural Language :: English
Classifier: License :: OSI Approved :: MIT License
Classifier: Operating System :: OS Independent
Classifier: Programming Language :: Python :: 3.5
Classifier: Programming Language :: Python :: 3.6
Classifier: Programming Language :: Python :: 3.7
Classifier: Programming Language :: Python :: 3.8
Classifier: Programming Language :: Python :: 3.9
Classifier: Programming Language :: Python :: 3.10
Classifier: Programming Language :: Python :: 3.11
Classifier: Programming Language :: Python :: 3.12
Classifier: Topic :: Text Processing :: Fonts
Classifier: Topic :: Text Editors
Classifier: Topic :: Text Processing :: General
Classifier: Topic :: Utilities
Classifier: Topic :: Multimedia
Classifier: Topic :: Printing
Requires-Python: >=3.5
License-File: LICENSE
License-File: AUTHORS.md
Provides-Extra: dev
Requires-Dist: coverage>=4.1; extra == "dev"
Requires-Dist: vulture>=1.0; extra == "dev"
Requires-Dist: bandit>=1.5.1; extra == "dev"
Requires-Dist: pydocstyle>=3.0.0; extra == "dev"
